{
  "name": "Nonalcoholic Dirty Lemon Tonic",
  "categories": [],
  "servings": 1,
  "minutes": 5,
  "source_url": "https://cooking.nytimes.com/recipes/1024102-nonalcoholic-dirty-lemon-tonic",
  "image_urls": [
    "https://static01.nyt.com/images/2023/04/12/multimedia/07martinirex2-na-qtlv/07martinirex2-na-qtlv-square640.jpg",
    "https://static01.nyt.com/images/2023/04/12/multimedia/07martinirex2-na-qtlv/07martinirex2-na-qtlv-videoSixteenByNineJumbo1600.jpg",
    "https://static01.nyt.com/images/2023/04/12/multimedia/07martinirex2-na-qtlv/07martinirex2-na-qtlv-superJumbo.jpg"
  ],
  "ingredients": [
    {
      "name": "dry tonic water",
      "amount": 4.0,
      "unit": "oz",
      "comment": "",
      "nutrition_infos": []
    }
  ],
  "instructions": [
    "In the bottom of a sturdy rocks glass, add the preserved lemon, lemon wheels and sugar. Muddle until the sugar dissolves and the lemon wheels release their juices. Add the ice to the glass and top with tonic water.",
    "Thread a skewer with a slice of preserved lemon rind, a few olives and a lemon half wheel; garnish."
  ],
  "notes": [],
  "nutrition_infos": []
}