{
  "name": "Classic Banana Split",
  "categories": [],
  "servings": 5,
  "minutes": 30,
  "source_url": "https://cooking.nytimes.com/recipes/1024310-classic-banana-split",
  "image_urls": [
    "https://static01.nyt.com/images/2023/06/21/multimedia/21BIG-APPErex1-kfvq/21BIG-APPErex1-kfvq-square640.jpg",
    "https://static01.nyt.com/images/2023/06/21/multimedia/21BIG-APPErex1-kfvq/21BIG-APPErex1-kfvq-videoSixteenByNineJumbo1600.jpg",
    "https://static01.nyt.com/images/2023/06/21/multimedia/21BIG-APPErex1-kfvq/21BIG-APPErex1-kfvq-superJumbo.jpg"
  ],
  "ingredients": [
    {
      "name": "5 grams walnut halves",
      "amount": 1.0,
      "unit": "",
      "comment": "",
      "nutrition_infos": []
    },
    {
      "name": "cup/59 milliliters maple syrup",
      "amount": 2.5,
      "unit": "",
      "comment": "",
      "nutrition_infos": []
    },
    {
      "name": "cup/59 milliliters honey",
      "amount": 2.5,
      "unit": "",
      "comment": "",
      "nutrition_infos": []
    },
    {
      "name": "cup/158 milliliters heavy cream",
      "amount": 2.5,
      "unit": "",
      "comment": "",
      "nutrition_infos": []
    },
    {
      "name": "honey",
      "amount": 3.0,
      "unit": "tbsp",
      "comment": "",
      "nutrition_infos": []
    },
    {
      "name": "dutch-process cocoa powder",
      "amount": 1.5,
      "unit": "tbsp",
      "comment": "",
      "nutrition_infos": []
    },
    {
      "name": "ounces/100 grams bittersweet chocolate",
      "amount": 3.5,
      "unit": "",
      "comment": "",
      "nutrition_infos": []
    },
    {
      "name": "vanilla extract",
      "amount": 1.5,
      "unit": "tsp",
      "comment": "",
      "nutrition_infos": []
    },
    {
      "name": "bananas",
      "amount": 2.0,
      "unit": "",
      "comment": "",
      "nutrition_infos": []
    }
  ],
  "instructions": [
    "Prepare the walnuts: Heat the oven to 350 degrees. Spread walnut halves evenly on a baking sheet and bake for 8 to 12 minutes, or until nuts smell toasted and are slightly darker in color. Transfer to a rack to cool.",
    "In a medium bowl, whisk together maple syrup, honey and salt. Add nuts (it’s OK if they are still hot) and stir to combine.",
    "Prepare the fudge: In a medium saucepan over medium heat, bring the cream, sugar, honey, cocoa and salt to a simmer, whisking until the sugar dissolves and the mixture thickens slightly, about 5 minutes.",
    "Stir in the chocolate and let cook until the chocolate melts, about 2 minutes. Stir in butter and vanilla (or liquor). Let cool slightly. Serve warm, not piping hot. If the fudge sauce begins to separate, vigorously whisk in 1 tablespoon hot water. Fudge sauce can be made up to 2 weeks ahead and stored in the fridge. Gently reheat before serving.",
    "Line a banana split bowl or other bowl with the banana halves. Top with scoops of ice cream, hot fudge and walnut sauce. Cover with whipped cream. Top with a cherry, if you like. Serve immediately."
  ],
  "notes": [],
  "nutrition_infos": []
}